WeiXinPaySDK/__init__.py
WeiXinPaySDK/version.py
WeiXinPaySDK/Pay/__init__.py
WeiXinPaySDK/Pay/bill.py
WeiXinPaySDK/Pay/order.py
WeiXinPaySDK/manage/__init__.py
WeiXinPaySDK/manage/pay_score_order.py
WeiXinPaySDK/manage/payscore.py
WeiXinPaySDK/manage/service_people.py
WeiXinPaySDK-0.0.4.dist-info/LICENSE
WeiXinPaySDK-0.0.4.dist-info/METADATA
WeiXinPaySDK-0.0.4.dist-info/WHEEL
WeiXinPaySDK-0.0.4.dist-info/top_level.txt
WeiXinPaySDK-0.0.4.dist-info/RECORD
