Metadata-Version: 2.1
Name: WeiXinPaySDK
Version: 0.0.4
Summary: WeiXinPaySDK是基于微信支付开发的sdk
Home-page: https://gitee.com/navysummer/WeiXinPaySDK.git
Author: navysummer
Author-email: navysummer@yeah.net
License: UNKNOWN
Platform: python
Classifier: Programming Language :: Python :: 3
Classifier: Programming Language :: Python :: 2
Classifier: Operating System :: OS Independent
Requires-Python: >=2.7
License-File: LICENSE
Requires-Dist: requests (~=2.27.1)
Requires-Dist: xmltodict (~=0.12.0)
Requires-Dist: qrcode (~=7.3.1)
Requires-Dist: Pillow (~=9.0.1)
Requires-Dist: lxml (~=4.8.0)
Requires-Dist: cryptography (~=36.0.2)
